<?xml version="1.0" encoding="utf-8"?>
<node id="HP">

  <node id="ACTIONS" address="0x00000000">
    <node id="RESET"          mask="0x000000001" permission="w"/>
    <node id="ENABLE"         mask="0x000000002" permission="w"/>
    <node id="DISABLE"        mask="0x000000004" permission="w"/>
    <node id="FREEZE"         mask="0x000000008" permission="w"/>
  </node>

  <node id="CONFIGS" address="0x00000001">
    <!-- <node id="THREADS"          mask="0x00000000F" parameters="default=3" permission="rw"/> -->
    <node id="INPUT_EN"         mask="0x000000001" parameters="default=1" permission="rw"/>
    <node id="OUTPUT_EN"        mask="0x000000002" parameters="default=1" permission="rw"/>
    <node id="FLUSH_MEM_RESET"  mask="0x000000004" parameters="default=1" permission="rw"/>
  </node>

  <!-- <node id="STATUS" address="0x00000002">
    <node id="ENABLED" mask="0x00000001" permission="r"/>
    <node id="READY"   mask="0x00000002" permission="r"/>
    <node id="ERROR"   mask="0x00000004" permission="r"/>
  </node> -->

  <node id="MDT_DT2R" address="0x00000003" module="file://MEM_INT_10A9D.xml"/>

</node>

